pengwann-0.5.2.dist-info/METADATA
pengwann-0.5.2.dist-info/WHEEL
pengwann-0.5.2.dist-info/licenses/LICENSE
pengwann/descriptors.py
pengwann/geometry.py
pengwann/interactions.py
pengwann/io.py
pengwann/occupations.py
pengwann/py.typed
pengwann/utils.py
pengwann/_geometry.pyi
pengwann/__init__.py
pengwann/_geometry.cp312-win32.pyd
pengwann-0.5.2.dist-info/RECORD
