Metadata-Version: 2.4
Name: pengwann
Version: 0.5.2
Classifier: Development Status :: 4 - Beta
Classifier: Intended Audience :: Science/Research
Classifier: License :: OSI Approved :: GNU General Public License v3 (GPLv3)
Classifier: Natural Language :: English
Classifier: Operating System :: OS Independent
Classifier: Programming Language :: Python :: 3.10
Classifier: Programming Language :: Python :: 3.11
Classifier: Programming Language :: Python :: 3.12
Classifier: Programming Language :: Python :: 3.13
Classifier: Topic :: Scientific/Engineering
Classifier: Topic :: Scientific/Engineering :: Chemistry
Classifier: Topic :: Scientific/Engineering :: Physics
Requires-Dist: numpy>=2
Requires-Dist: scipy
Requires-Dist: tqdm
Requires-Dist: typing-extensions>=4.12,<5.0
Requires-Dist: myst-nb ; extra == 'docs'
Requires-Dist: numpydoc ; extra == 'docs'
Requires-Dist: pydata-sphinx-theme ; extra == 'docs'
Requires-Dist: sphinx ; extra == 'docs'
Requires-Dist: sphinxcontrib-bibtex ; extra == 'docs'
Requires-Dist: tomli ; extra == 'docs'
Provides-Extra: docs
License-File: LICENSE
Summary: Computation of chemical bonding descriptors from Wannier functions
Author-email: "Patrick J. Taylor" <pjt35@bath.ac.uk>
Maintainer-email: "Patrick J. Taylor" <pjt35@bath.ac.uk>
Requires-Python: >=3.10
Project-URL: homepage, https://github.com/PatrickJTaylor/pengWann
